{"_id":"node-icu-charset-detector","_rev":"19-fdd8b7c1fc71f6510a7c5d7ce58e98b7","name":"node-icu-charset-detector","description":"Simple binding for ICU charset detector","dist-tags":{"latest":"0.1.0"},"versions":{"0.0.1":{"name":"node-icu-charset-detector","version":"0.0.1","main":"./build/default/lib/node-icu-charset-detector","description":"Simple binding for ICU charset detector","keywords":["charset-detection","icu"],"repository":{"type":"git","path":"git://github.com/mooz/node-icu-charset-detector.git","url":""},"homepage":"http://github.com/mooz/node-icu-charset-detector","bugs":{"name":"http://github.com/mooz/node-icu-charset-detector/issues"},"author":{"name":"Masafumi Oyamada","email":"stillpedant@gmail.com","url":"http://mooz.github.com/"},"licenses":[{"type":"MIT"}],"engines":{"node":">=0.6"},"scripts":{"preinstall":"node-waf configure","install":"node-waf build install"},"_npmUser":{"name":"mooz","email":"stillpedant@gmail.com"},"_id":"node-icu-charset-detector@0.0.1","dependencies":{},"devDependencies":{},"optionalDependencies":{},"_engineSupported":true,"_npmVersion":"1.1.1","_nodeVersion":"v0.6.11","_defaultsLoaded":true,"dist":{"shasum":"b2cfd2a76689f074aa86a6531a3e11b18e8164d4","tarball":"http://registry.npmjs.org/node-icu-charset-detector/-/node-icu-charset-detector-0.0.1.tgz"},"maintainers":[{"name":"mooz","email":"stillpedant@gmail.com"}],"directories":{}},"0.0.2":{"name":"node-icu-charset-detector","version":"0.0.2","main":"./build/default/lib/node-icu-charset-detector","description":"Simple binding for ICU charset detector","keywords":["charset-detection","icu"],"repository":{"type":"git","path":"git://github.com/mooz/node-icu-charset-detector.git","url":""},"homepage":"http://github.com/mooz/node-icu-charset-detector","bugs":{"name":"http://github.com/mooz/node-icu-charset-detector/issues"},"author":{"name":"Masafumi Oyamada","email":"stillpedant@gmail.com","url":"http://mooz.github.com/"},"licenses":[{"type":"MIT"}],"engines":{"node":">=0.6"},"scripts":{"preinstall":"node-waf configure","install":"node-waf build install"},"_npmUser":{"name":"mooz","email":"stillpedant@gmail.com"},"_id":"node-icu-charset-detector@0.0.2","dependencies":{},"devDependencies":{},"optionalDependencies":{},"_engineSupported":true,"_npmVersion":"1.1.1","_nodeVersion":"v0.6.11","_defaultsLoaded":true,"dist":{"shasum":"7ac4785b3226e8ab2bf095e541adecf7b7e36873","tarball":"http://registry.npmjs.org/node-icu-charset-detector/-/node-icu-charset-detector-0.0.2.tgz"},"maintainers":[{"name":"mooz","email":"stillpedant@gmail.com"}],"directories":{}},"0.0.3":{"name":"node-icu-charset-detector","version":"0.0.3","main":"./build/default/lib/node-icu-charset-detector","description":"Simple binding for ICU charset detector","keywords":["charset-detection","icu"],"repository":{"type":"git","path":"git://github.com/mooz/node-icu-charset-detector.git","url":""},"homepage":"http://github.com/mooz/node-icu-charset-detector","bugs":{"name":"http://github.com/mooz/node-icu-charset-detector/issues"},"author":{"name":"Masafumi Oyamada","email":"stillpedant@gmail.com","url":"http://mooz.github.com/"},"licenses":[{"type":"MIT"}],"engines":{"node":">=0.6"},"scripts":{"preinstall":"node-waf configure","install":"node-waf build install"},"_npmUser":{"name":"mooz","email":"stillpedant@gmail.com"},"_id":"node-icu-charset-detector@0.0.3","dependencies":{},"devDependencies":{},"optionalDependencies":{},"_engineSupported":true,"_npmVersion":"1.1.1","_nodeVersion":"v0.6.11","_defaultsLoaded":true,"dist":{"shasum":"e12554f552d3b7842f38a71f4644098115f9bdf7","tarball":"http://registry.npmjs.org/node-icu-charset-detector/-/node-icu-charset-detector-0.0.3.tgz"},"maintainers":[{"name":"mooz","email":"stillpedant@gmail.com"}],"directories":{}},"0.0.4":{"name":"node-icu-charset-detector","version":"0.0.4","main":"./build/default/lib/node-icu-charset-detector","description":"Simple binding for ICU charset detector","keywords":["charset-detection","icu"],"repository":{"type":"git","path":"git://github.com/mooz/node-icu-charset-detector.git","url":""},"homepage":"http://github.com/mooz/node-icu-charset-detector","bugs":{"name":"http://github.com/mooz/node-icu-charset-detector/issues"},"author":{"name":"Masafumi Oyamada","email":"stillpedant@gmail.com","url":"http://mooz.github.com/"},"licenses":[{"type":"MIT"}],"engines":{"node":">=0.6"},"_npmUser":{"name":"mooz","email":"stillpedant@gmail.com"},"_id":"node-icu-charset-detector@0.0.4","scripts":{"preinstall":"node-waf clean || (exit 0); node-waf configure build"},"dependencies":{},"devDependencies":{},"optionalDependencies":{},"_engineSupported":true,"_npmVersion":"1.1.1","_nodeVersion":"v0.6.11","_defaultsLoaded":true,"dist":{"shasum":"77dbcaa46c637c40a0cb1c5f6f6b22c76c23bf3e","tarball":"http://registry.npmjs.org/node-icu-charset-detector/-/node-icu-charset-detector-0.0.4.tgz"},"maintainers":[{"name":"mooz","email":"stillpedant@gmail.com"}],"directories":{}},"0.0.5":{"name":"node-icu-charset-detector","version":"0.0.5","main":"./build/Release/node-icu-charset-detector","description":"Simple binding for ICU charset detector","keywords":["charset-detection","icu"],"repository":{"type":"git","path":"git://github.com/mooz/node-icu-charset-detector.git","url":""},"homepage":"http://github.com/mooz/node-icu-charset-detector","bugs":{"name":"http://github.com/mooz/node-icu-charset-detector/issues"},"author":{"name":"Masafumi Oyamada","email":"stillpedant@gmail.com","url":"http://mooz.github.com/"},"licenses":[{"type":"MIT"}],"engines":{"node":">=0.6"},"_npmUser":{"name":"mooz","email":"stillpedant@gmail.com"},"_id":"node-icu-charset-detector@0.0.5","scripts":{"preinstall":"node-waf clean || (exit 0); node-waf configure build"},"dependencies":{},"devDependencies":{},"optionalDependencies":{},"_engineSupported":true,"_npmVersion":"1.1.1","_nodeVersion":"v0.6.11","_defaultsLoaded":true,"dist":{"shasum":"161d19a6d18dcffdbfffdb6c8b92dab2947edfd8","tarball":"http://registry.npmjs.org/node-icu-charset-detector/-/node-icu-charset-detector-0.0.5.tgz"},"maintainers":[{"name":"mooz","email":"stillpedant@gmail.com"}],"directories":{}},"0.0.6":{"name":"node-icu-charset-detector","version":"0.0.6","main":"./node-icu-charset-detector.js","description":"Simple binding for ICU charset detector","keywords":["charset-detection","icu"],"repository":{"type":"git","path":"git://github.com/mooz/node-icu-charset-detector.git"},"homepage":"http://github.com/mooz/node-icu-charset-detector","bugs":"http://github.com/mooz/node-icu-charset-detector/issues","author":{"name":"Masafumi Oyamada","email":"stillpedant@gmail.com","url":"http://mooz.github.com/"},"licenses":[{"type":"MIT"}],"engines":{"node":">=0.6"},"scripts":{"install":"node-gyp rebuild"},"gypfile":true,"_id":"node-icu-charset-detector@0.0.6","dist":{"shasum":"9a0509363080eddebf291228ffc73b6153970603","tarball":"http://registry.npmjs.org/node-icu-charset-detector/-/node-icu-charset-detector-0.0.6.tgz"},"_from":".","_npmVersion":"1.2.10","_npmUser":{"name":"mooz","email":"stillpedant@gmail.com"},"maintainers":[{"name":"mooz","email":"stillpedant@gmail.com"}],"directories":{}},"0.0.7":{"name":"node-icu-charset-detector","version":"0.0.7","main":"./node-icu-charset-detector.js","description":"Simple binding for ICU charset detector","keywords":["charset-detection","icu"],"repository":{"type":"git","path":"git://github.com/mooz/node-icu-charset-detector.git"},"homepage":"http://github.com/mooz/node-icu-charset-detector","bugs":{"url":"http://github.com/mooz/node-icu-charset-detector/issues"},"author":{"name":"Masafumi Oyamada","email":"stillpedant@gmail.com","url":"http://mooz.github.com/"},"licenses":[{"type":"MIT"}],"engines":{"node":">=0.6"},"scripts":{"install":"node-gyp rebuild"},"gypfile":true,"_id":"node-icu-charset-detector@0.0.7","dist":{"shasum":"832867d4e70cc666a616339ff6637bad039c7d1f","tarball":"http://registry.npmjs.org/node-icu-charset-detector/-/node-icu-charset-detector-0.0.7.tgz"},"_from":".","_npmVersion":"1.2.25","_npmUser":{"name":"mooz","email":"stillpedant@gmail.com"},"maintainers":[{"name":"mooz","email":"stillpedant@gmail.com"}],"directories":{}},"0.1.0":{"name":"node-icu-charset-detector","version":"0.1.0","main":"./node-icu-charset-detector.js","description":"Simple binding for ICU charset detector","keywords":["charset-detection","icu"],"repository":{"type":"git","path":"git://github.com/mooz/node-icu-charset-detector.git"},"homepage":"http://github.com/mooz/node-icu-charset-detector","bugs":{"url":"http://github.com/mooz/node-icu-charset-detector/issues"},"author":{"name":"Masafumi Oyamada","email":"stillpedant@gmail.com","url":"http://mooz.github.com/"},"licenses":[{"type":"MIT"}],"engines":{"node":">=0.6"},"dependencies":{"nan":"^1.6.2"},"scripts":{"install":"node-gyp rebuild"},"gypfile":true,"gitHead":"628e6e011ea32ee3ba310f3c379b6103d9f3d1a7","_id":"node-icu-charset-detector@0.1.0","_shasum":"df8132bde83345cf791b8967b96dae4ae3f7c221","_from":".","_npmVersion":"2.5.1","_nodeVersion":"0.12.0","_npmUser":{"name":"mooz","email":"stillpedant@gmail.com"},"maintainers":[{"name":"mooz","email":"stillpedant@gmail.com"}],"dist":{"shasum":"df8132bde83345cf791b8967b96dae4ae3f7c221","tarball":"http://registry.npmjs.org/node-icu-charset-detector/-/node-icu-charset-detector-0.1.0.tgz"},"directories":{}}},"readme":"# ICU Character Set Detection for Node.js\n\n>Character set detection is the process of determining the character set, or encoding, of character data in an unknown format.\n\nA simple binding of ICU character set detection (http://userguide.icu-project.org/conversion/detection) for Node.js.\n\n## Installation\n\nAt first, install `libicu` into your system (See [this instruction](#installing-icu) for details).\n\nAfter that, install `node-icu-charset-detector` from npm.\n\n    ```npm install node-icu-charset-detector```\n\n### Installing ICU\n\n#### Linux\n\n* Debian (Ubuntu)\n\n    ```apt-get install libicu-dev```\n\n* Gentoo\n\n    ```emerge icu```\n    \n* Fedora/CentOS\n\n    ```yum install libicu-devel```\n\n\n#### OSX\n\n* MacPorts\n\n    ```port install icu +devel```\n\n* Homebrew\n\n    ```shell\n    brew install icu4c\n    brew link icu4c --force\n    ```\n\n    If experiencing issues with 'homebrew' installing version 50.1 of icu4c, try the following:\n\n    ```shell\n    brew search icu4c\n    brew tap homebrew/versions\n    brew versions icu4c\n    cd $(brew --prefix) && git pull --rebase\n    git checkout c25fd2f $(brew --prefix)/Library/Formula/icu4c.rb\n    brew install icu4c\n    ```\n\n* From source\n\n    ```shell\n    curl -O http://download.icu-project.org/files/icu4c/52.1/icu4c-52_1-src.tgz\n    tar xzvf icu4c-4_4_2-src.tgz\n    cd icu/source\n    chmod +x runConfigureICU configure install-sh\n    ./runConfigureICU MacOSX\n    make\n    sudo make install\n    xcode-select --install\n    ```\n\n## Usage\n\n### Simple usage\n\n`node-icu-charset-detector` provides a function `detectCharset(buffer)`, where `buffer` is an instance of `Buffer` whose charset should be detected.\n\n```javascript\nvar charsetDetector = require(\"node-icu-charset-detector\");\n\nvar buffer = fs.readFileSync(\"/path/to/the/file\");\nvar charset = charsetDetector.detectCharset(buffer);\n\nconsole.log(\"charset name: \" + charset.toString());\nconsole.log(\"language: \" + charset.language);\nconsole.log(\"detection confidence: \" + charset.confidence);\n```\n\n`detectCharset(buffer)` returns the detected charset name for `buffer`, and the returned charset name has two extra properties `language` and `confidence`:\n\n- `charset.language`\n  - language name for the detected character set.\n- `charset.confidence`\n  - confidence of the charset detection for `charset`.\n\n### Leveraging node-iconv\n\nSince ICU itself does not have a feature to convert character sets, you may need to use `node-iconv` (https://github.com/bnoordhuis/node-iconv), which has a powerful character sets converting feature.\n\nHere is a simple example to leverage `node-iconv` to convert character sets not supported by Node itself.\n\n```javascript\nfunction bufferToString(buffer) {\n  var charsetDetector = require(\"node-icu-charset-detector\");\n  var charset = charsetDetector.detectCharset(buffer).toString();\n\n  try {\n    return buffer.toString(charset);\n  } catch (x) {\n    var Iconv = require(\"iconv\").Iconv;\n    var charsetConverter = new Iconv(charset, \"utf8\");\n    return charsetConverter.convert(buffer).toString();\n  }\n}\n\nvar buffer = fs.readFileSync(\"/path/to/the/file\");\nvar bufferString = bufferToString(buffer);\n```\n","maintainers":[{"name":"mooz","email":"stillpedant@gmail.com"}],"time":{"modified":"2015-02-18T14:34:09.879Z","created":"2012-05-17T07:03:07.125Z","0.0.1":"2012-05-17T07:03:09.929Z","0.0.2":"2012-05-17T07:05:31.021Z","0.0.3":"2012-05-17T07:30:17.583Z","0.0.4":"2012-11-24T15:02:46.379Z","0.0.5":"2012-11-26T04:23:05.641Z","0.0.6":"2013-02-23T13:36:07.814Z","0.0.7":"2013-09-04T13:39:05.122Z","0.1.0":"2015-02-18T14:34:09.879Z"},"author":{"name":"Masafumi Oyamada","email":"stillpedant@gmail.com","url":"http://mooz.github.com/"},"repository":{"type":"git","path":"git://github.com/mooz/node-icu-charset-detector.git"},"homepage":"http://github.com/mooz/node-icu-charset-detector","keywords":["charset-detection","icu"],"bugs":{"url":"http://github.com/mooz/node-icu-charset-detector/issues"},"readmeFilename":"README.md","users":{"luhuan":true,"nex":true},"_attachments":{},"_etag":"\"9FA19YYC7XDC7389UYO5R6D8Q\""}